{
    "home": {
        "hero": {
            "switchLanguage": "हिंदी पर स्विच करें",
            "title": "रंगिश",
            "subtitle": "कला और विरासत का उत्सव",
            "button1": "गैलरी देखें",
            "button2": "और जानें"
        },
        "aboutMe": {
            "title": "मेरे बारे में",
            "description": "मैं एक उत्साही फोटोग्राफर हूँ जिसे दुनिया की सुंदरता को कैप्चर करने का शौक है।"
        },
        "featuredProducts": {
            "title": "विशेष उत्पाद"
        },
        "contactMe": {
            "title": "मुझसे संपर्क करें",
            "description": "सहयोग या पूछताछ के लिए बेझिझक संपर्क करें।"
        }
    },
    "gallery": {
        "title": "गैलरी",
        "description": "मेरे पेंटिंग और फोटोग्राफ़ संग्रह का अन्वेषण करें।"
    }
}